mc_simulation/__init__.py
mc_simulation/average_models.py
mc_simulation/monte_carlo_sim.py
mc_simulation/volatility_models.py
mc_simulation-0.0.3.dist-info/LICENSE
mc_simulation-0.0.3.dist-info/METADATA
mc_simulation-0.0.3.dist-info/WHEEL
mc_simulation-0.0.3.dist-info/top_level.txt
mc_simulation-0.0.3.dist-info/RECORD
